nostr/__init__.py
nostr/_version.py
nostr/bech32.py
nostr/delegation.py
nostr/event.py
nostr/filter.py
nostr/key.py
nostr/message_pool.py
nostr/message_type.py
nostr/pow.py
nostr/relay.py
nostr/relay_manager.py
nostr/subscription.py
nostr-0.0.2.dist-info/LICENSE
nostr-0.0.2.dist-info/METADATA
nostr-0.0.2.dist-info/WHEEL
nostr-0.0.2.dist-info/top_level.txt
nostr-0.0.2.dist-info/RECORD
