Metadata-Version: 2.1
Name: nostr
Version: 0.0.2
Summary: A Python library for making Nostr clients
Author-email: Jeff Thibault <jdthibault2@gmail.com>
License: MIT License
Project-URL: Homepage, https://github.com/jeffthibault/python-nostr
Classifier: Operating System :: POSIX :: Linux
Classifier: Operating System :: Microsoft :: Windows
Classifier: Operating System :: MacOS :: MacOS X
Requires-Python: >3.6.0
Provides-Extra: test
License-File: LICENSE
